naveeeen/__init__.py
naveeeen/naveeeen.py
naveeeen-0.0.8.dist-info/METADATA
naveeeen-0.0.8.dist-info/WHEEL
naveeeen-0.0.8.dist-info/licenses/LICENCE
naveeeen-0.0.8.dist-info/RECORD
