Metadata-Version: 2.1
Name: naveeeen
Version: 0.0.8
Summary: See the difference, with/out naveeeen.
Project-URL: Homepage, https://github.com/navpypi/naveeeen-pypi
Project-URL: Bug Tracker, https://github.com/navpypi/naveeeen-pypi
Author-email: naveen v <navpypi@gmail.com>
License-File: LICENCE
Classifier: License :: OSI Approved :: MIT License
Classifier: Operating System :: OS Independent
Classifier: Programming Language :: Python :: 3
Requires-Python: >=3.5
